MANIFEST.in
setup.py
tests/__init__.py
tests/base.py
tests/test_version.py
thumbor_web/__init__.py
thumbor_web/admin.py
thumbor_web/app.py
thumbor_web/assets.py
thumbor_web/manage.py
thumbor_web/models.py
thumbor_web/run.py
thumbor_web/version.py
thumbor_web.egg-info/PKG-INFO
thumbor_web.egg-info/SOURCES.txt
thumbor_web.egg-info/dependency_links.txt
thumbor_web.egg-info/entry_points.txt
thumbor_web.egg-info/requires.txt
thumbor_web.egg-info/top_level.txt
thumbor_web/config/__init__.py
thumbor_web/config/local.conf
thumbor_web/handlers/__init__.py
thumbor_web/handlers/home.py
thumbor_web/migrations/env.py
thumbor_web/migrations/versions/49fcf2d3f007_initial_admin_users.py
thumbor_web/migrations/versions/53ef6444c12_creating_testimonial_model.py
thumbor_web/migrations/versions/5566da8254ae_initial_testimonies.py
thumbor_web/migrations/versions/a927bafc28e_creating_user_model.py
thumbor_web/static/css/thumbor-web.app.min.css
thumbor_web/static/images/common-s2ae6b27cad.png
thumbor_web/static/images/retina-s5bf82002af.png
thumbor_web/static/images/common/arrow-bottom.png
thumbor_web/static/images/common/arrow.png
thumbor_web/static/images/common/benefits-designers-desktop.png
thumbor_web/static/images/common/benefits-designers.png
thumbor_web/static/images/common/benefits-developers-desktop.png
thumbor_web/static/images/common/benefits-developers.png
thumbor_web/static/images/common/benefits-operations-desktop.png
thumbor_web/static/images/common/benefits-operations.png
thumbor_web/static/images/common/benefits-project-desktop.png
thumbor_web/static/images/common/benefits-project.png
thumbor_web/static/images/common/bernardo-mobile.png
thumbor_web/static/images/common/bernardo.png
thumbor_web/static/images/common/burger.png
thumbor_web/static/images/common/caricio-mobile.png
thumbor_web/static/images/common/caricio.png
thumbor_web/static/images/common/cezar-mobile.png
thumbor_web/static/images/common/cezar.png
thumbor_web/static/images/common/fabio-mobile.png
thumbor_web/static/images/common/fabio.png
thumbor_web/static/images/common/globocom_retina.png
thumbor_web/static/images/common/logo-mobile.png
thumbor_web/static/images/common/logo-small.png
