Metadata-Version: 1.1
Name: thumbor-web
Version: 0.3.1
Summary: thumbor website
Home-page: https://github.com/thumbor/thumbor-web
Author: Bernardo Heynemann
Author-email: heynemann@gmail.com
License: MIT
Keywords: thumbor web
Platform: UNKNOWN
Classifier: Development Status :: 4 - Beta
Classifier: Intended Audience :: Developers
Classifier: License :: OSI Approved :: MIT License
Classifier: Natural Language :: English
Classifier: Operating System :: Unix
Classifier: Programming Language :: Python :: 2.7
Classifier: Operating System :: OS Independent
